{
	"info": {
		"_postman_id": "8f10672d-8c43-447f-aac0-fc0981d7fc22",
		"name": "BudgetMaster",
		"schema": "https://schema.getpostman.com/json/collection/v2.1.0/collection.json",
		"_exporter_id": "24310880"
	},
	"item": [
		{
			"name": "login",
			"request": {
				"method": "POST",
				"header": [],
				"body": {
					"mode": "raw",
					"raw": "{\r\n    \"email\" :\"test@gmail.com\",\r\n    \"password\" : \"testest\"\r\n}\r\n",
					"options": {
						"raw": {
							"language": "json"
						}
					}
				},
				"url": {
					"raw": "http://localhost:8080/user/login",
					"protocol": "http",
					"host": [
						"localhost"
					],
					"port": "8080",
					"path": [
						"user",
						"login"
					]
				}
			},
			"response": []
		},
		{
			"name": "post depenses",
			"request": {
				"method": "POST",
				"header": [],
				"body": {
					"mode": "raw",
					"raw": "{\r\n    \"email\" :\"test@gmail.com\",\r\n    \"password\" : \"testest\"\r\n}\r\n",
					"options": {
						"raw": {
							"language": "json"
						}
					}
				},
				"url": {
					"raw": "http://localhost:8080/depenses/depenses",
					"protocol": "http",
					"host": [
						"localhost"
					],
					"port": "8080",
					"path": [
						"depenses",
						"depenses"
					]
				}
			},
			"response": []
		},
		{
			"name": "register",
			"request": {
				"method": "POST",
				"header": [],
				"url": {
					"raw": "http://localhost:8080/user/register",
					"protocol": "http",
					"host": [
						"localhost"
					],
					"port": "8080",
					"path": [
						"user",
						"register"
					]
				}
			},
			"response": []
		},
		{
			"name": "get All Depenses",
			"request": {
				"method": "GET",
				"header": [],
				"url": {
					"raw": "http://localhost:8080/depenses/getDepenses",
					"protocol": "http",
					"host": [
						"localhost"
					],
					"port": "8080",
					"path": [
						"depenses",
						"getDepenses"
					]
				}
			},
			"response": []
		},
		{
			"name": "get last depenses",
			"request": {
				"method": "GET",
				"header": [],
				"url": {
					"raw": "http://localhost:8080/depenses/getLastDepenses",
					"protocol": "http",
					"host": [
						"localhost"
					],
					"port": "8080",
					"path": [
						"depenses",
						"getLastDepenses"
					]
				}
			},
			"response": []
		},
		{
			"name": "get total mois en cours",
			"request": {
				"method": "GET",
				"header": [],
				"url": {
					"raw": "http://localhost:8080/depenses/totalMoisEnCours",
					"protocol": "http",
					"host": [
						"localhost"
					],
					"port": "8080",
					"path": [
						"depenses",
						"totalMoisEnCours"
					]
				}
			},
			"response": []
		}
	]
}